MANIFEST.in
README.rst
setup.cfg
setup.py
clocwalk/.DS_Store
clocwalk/__init__.py
clocwalk/__init__.pyc
clocwalk/cli.py
clocwalk/cli.pyc
clocwalk/conf.yaml
clocwalk/dns.py
clocwalk.egg-info/PKG-INFO
clocwalk.egg-info/SOURCES.txt
clocwalk.egg-info/dependency_links.txt
clocwalk.egg-info/entry_points.txt
clocwalk.egg-info/not-zip-safe
clocwalk.egg-info/requires.txt
clocwalk.egg-info/top_level.txt
clocwalk/__pycache__/__init__.cpython-37.pyc
clocwalk/__pycache__/cli.cpython-37.pyc
clocwalk/__pycache__/dns.cpython-37.pyc
clocwalk/libs/__init__.py
clocwalk/libs/__init__.pyc
clocwalk/libs/__pycache__/__init__.cpython-37.pyc
clocwalk/libs/analyzer/__init__.py
clocwalk/libs/analyzer/gradle.py
clocwalk/libs/analyzer/mvn.py
clocwalk/libs/analyzer/nodejs.py
clocwalk/libs/analyzer/pip.py
clocwalk/libs/analyzer/ruby.py
clocwalk/libs/analyzer/__pycache__/__init__.cpython-37.pyc
clocwalk/libs/analyzer/__pycache__/gradle.cpython-37.pyc
clocwalk/libs/analyzer/__pycache__/mvn.cpython-37.pyc
clocwalk/libs/analyzer/__pycache__/nodejs.cpython-37.pyc
clocwalk/libs/analyzer/__pycache__/pip.cpython-37.pyc
clocwalk/libs/analyzer/__pycache__/ruby.cpython-37.pyc
clocwalk/libs/core/__init__.py
clocwalk/libs/core/__init__.pyc
clocwalk/libs/core/ansistrm.py
clocwalk/libs/core/clocwrapper.py
clocwalk/libs/core/clocwrapper.pyc
clocwalk/libs/core/cmdline.py
clocwalk/libs/core/cmdline.pyc
clocwalk/libs/core/common.py
clocwalk/libs/core/common.pyc
clocwalk/libs/core/data.py
clocwalk/libs/core/data.pyc
clocwalk/libs/core/datatype.py
clocwalk/libs/core/datatype.pyc
clocwalk/libs/core/datatype_cache.py
clocwalk/libs/core/datatype_cache.pyc
clocwalk/libs/core/db_helper.py
clocwalk/libs/core/db_helper.pyc
clocwalk/libs/core/exception.py
clocwalk/libs/core/exception.pyc
clocwalk/libs/core/http.py
clocwalk/libs/core/log.py
clocwalk/libs/core/log.pyc
clocwalk/libs/core/mysql_helper.py
clocwalk/libs/core/option.py
clocwalk/libs/core/option.pyc
clocwalk/libs/core/settings.py
clocwalk/libs/core/settings.pyc
clocwalk/libs/core/update.py
clocwalk/libs/core/update.pyc
clocwalk/libs/core/update_mysql.py
clocwalk/libs/core/__pycache__/__init__.cpython-37.pyc
clocwalk/libs/core/__pycache__/clocwrapper.cpython-37.pyc
