Metadata-Version: 2.1
Name: clocwalk
Version: 2.0.0
Summary: Project code and dependent component analysis tools.
Home-page: https://github.com/MyKings/clocwalk
Author: MyKings
Author-email: xsseroot@gmail.com
License: UNKNOWN
Platform: UNKNOWN
Provides-Extra: dev
Provides-Extra: test
Provides-Extra: docs
Provides-Extra: build
